dsa/__init__.py
dsa/ztest.py
dsa/da/__init__.py
dsa/da/util.py
dsa/da/util_autofeature.py
dsa/da/util_automl.py
dsa/da/util_credit.py
dsa/da/util_csv.py
dsa/da/util_date.py
dsa/da/util_deep.py
dsa/da/util_feature.py
dsa/da/util_import.py
dsa/da/util_model.py
dsa/da/util_optim.py
dsa/da/util_pipeline.py
dsa/da/util_plot.py
dsa/da/util_sql.py
dsa/da/util_stat.py
dsa/da/util_text.py
dsa/da/ztest.py
dsa/da/model/__init__.py
dsa/da/model/auto_sklearn_example.py
dsa/da/model/column_encoder.py
dsa/da/model/features/__init__.py
dsa/da/model/features/data/__init__.py
dsa/da/model/features/data_exploration/__init__.py
dsa/da/model/features/data_exploration/explore.py
dsa/da/model/features/feature_cleaning/__init__.py
dsa/da/model/features/feature_cleaning/missing_data.py
dsa/da/model/features/feature_cleaning/outlier.py
dsa/da/model/features/feature_cleaning/rare_values.py
dsa/da/model/features/feature_engineering/__init__.py
dsa/da/model/features/feature_engineering/discretization.py
dsa/da/model/features/feature_engineering/encoding.py
dsa/da/model/features/feature_engineering/transformation.py
dsa/da/model/features/feature_selection/__init__.py
dsa/da/model/features/feature_selection/embedded_method.py
dsa/da/model/features/feature_selection/feature_shuffle.py
dsa/da/model/features/feature_selection/filter_method.py
dsa/da/model/features/feature_selection/hybrid.py
dsa/da/model/hunga_bunga/__init__.py
dsa/da/model/hunga_bunga/classification.py
dsa/da/model/hunga_bunga/core.py
dsa/da/model/hunga_bunga/params.py
dsa/da/model/hunga_bunga/regression.py
dsa-13.3.0.dist-info/METADATA
dsa-13.3.0.dist-info/WHEEL
dsa-13.3.0.dist-info/top_level.txt
dsa-13.3.0.dist-info/RECORD
