Metadata-Version: 2.1
Name: dsa
Version: 13.3.0
Summary: Data Science Library, (automation, dataset shift, ..)
Home-page: https://github.com/arita37/
Author: Kevin Noel
Author-email: brookm291@gmail.com
License: UNKNOWN
Platform: UNKNOWN
